{
  "context": {
    "action": "on_track",
    "transaction_id": "9b6ce26b-6cb8-4459-bb35-eeca29074a2f",
    "message_id": "cde9b792-f87c-4f8c-8582-7c42a21d4738",
    "city": "std:080",
    "domain": "ONDC:RET11",
    "country": "IND",
    "core_version": "1.2.0",
    "timestamp": "2024-01-15T10:25:46.711Z",
    "bap_id": "buyer-app-preprod-v2.ondc.org",
    "bap_uri": "https://buyer-app-preprod-v2.ondc.org/protocol/v1",
    "bpp_id": "api.test.esamudaay.com/ondc/sdk/bpp/retail/esamudaay",
    "bpp_uri": "https://api.test.esamudaay.com/ondc/sdk/bpp/retail/esamudaay",
    "ttl": "PT30S"
  },
  "message": {
    "tracking": {
      "id": "Fulfillment1",
      "location": {
        "gps": "12.9816214,77.5925303",
        "time": {
          "timestamp": "2024-01-15T10:25:46.708Z"
        },
        "updated_at": "2024-01-15T10:25:46.708Z"
      },
      "status": "active"
    }
  }
}