{
  "context": {
    "domain": "ONDC:RET10",
    "country": "IND",
    "city": "std:080",
    "action": "status",
    "core_version": "1.2.0",
    "bap_id": "buyer-app-preprod-v2.ondc.org",
    "bap_uri": "https://buyer-app-preprod-v2.ondc.org/protocol/v1",
    "bpp_uri": "https://preprod-ondc.airpay.ninja/bapl",
    "transaction_id": "783329d4-3e1d-495c-b5c3-cb832551589f",
    "message_id": "205c11e9-bb9b-4497-b8ba-e3fdaf83b872",
    "timestamp": "2025-01-09T10:03:49.066Z",
    "bpp_id": "preprod-ondc.airpay.ninja",
    "ttl": "PT30S"
  },
  "message": {
    "order_id": "2025-01-09-434034"
  }
}
