{
  "context": {
    "domain": "ONDC:RET10",
    "action": "on_select",
    "core_version": "1.2.0",
    "bap_id": "beta.mystore.in",
    "bap_uri": "https://beta.mystore.in/ondc/1.0/",
    "bpp_id": "ondc-api.kiko.live/ondc-seller-v2",
    "bpp_uri": "https://ondc-api.kiko.live/ondc-seller-v2",
    "transaction_id": "80f8f917-c331-4b0e-9fcf-18ca0e86f206",
    "message_id": "adfac0d9-8f45-4117-9006-28859b4ec6d6",
    "city": "std:022",
    "country": "IND",
    "timestamp": "2024-03-12T11:25:42.283Z"
  },
  "message": {
    "order": {
      "provider": {
        "id": "6386154b42674fabf7bdabf4",
        "locations": [
          {
            "id": "location-6386154b42674fabf7bdabf4"
          }
        ]
      },
      "items": [
        {
          "fulfillment_id": "fulfillment-6386154b42674fabf7bdabf4",
          "id": "65bc8a50dd2fbfc824b428b7"
        },
        {
          "fulfillment_id": "fulfillment-6386154b42674fabf7bdabf4",
          "id": "65bcf1988bef71377b3f3f22"
        }
      ],
      "fulfillments": [
        {
          "id": "fulfillment-6386154b42674fabf7bdabf4",
          "type": "Delivery",
          "@ondc/org/provider_name": "Vijendra Grocery Store",
          "tracking": false,
          "@ondc/org/category": "Standard Delivery",
          "@ondc/org/TAT": "PT24H",
          "state": {
            "descriptor": {
              "code": "Serviceable"
            }
          }
        }
      ],
      "quote": {
        "price": {
          "currency": "INR",
          "value": "4893.00"
        },
        "breakup": [
          {
            "@ondc/org/item_id": "65bc8a50dd2fbfc824b428b7",
            "@ondc/org/item_quantity": {
              "count": 2
            },
            "title": "7 Up Nimbooz Masala Soda - With Real Lemon Juice, 500 Ml",
            "@ondc/org/title_type": "item",
            "price": {
              "currency": "INR",
              "value": "70.00"
            },
            "item": {
              "quantity": {
                "available": {
                  "count": "99"
                },
                "maximum": {
                  "count": "99"
                }
              },
              "price": {
                "currency": "INR",
                "value": "35.00"
              }
            }
          },
          {
            "@ondc/org/item_id": "65bcf1988bef71377b3f3f22",
            "@ondc/org/item_quantity": {
              "count": 2
            },
            "title": "Amul ghee",
            "@ondc/org/title_type": "item",
            "price": {
              "currency": "INR",
              "value": "4800.00"
            },
            "item": {
              "quantity": {
                "available": {
                  "count": "99"
                },
                "maximum": {
                  "count": "99"
                }
              },
              "price": {
                "currency": "INR",
                "value": "2400.00"
              }
            }
          },
          {
            "@ondc/org/item_id": "fulfillment-6386154b42674fabf7bdabf4",
            "title": "Delivery charges",
            "@ondc/org/title_type": "delivery",
            "price": {
              "currency": "INR",
              "value": "20"
            }
          },
          {
            "@ondc/org/item_id": "fulfillment-6386154b42674fabf7bdabf4",
            "title": "Convenience Fee",
            "@ondc/org/title_type": "misc",
            "price": {
              "currency": "INR",
              "value": "3"
            }
          }
        ],
        "ttl": "PT6H"
      }
    }
  }
}