{
    "context": {
        "domain": "nic2004:60232",
        "country": "IND",
        "city": "std:0172",
        "action": "update",
        "core_version": "1.2.0",
        "bap_id": "logistics_buyer.com",
        "bap_uri": "https://f5d5-115-240-127-98.ngrok-free.app",
        "transaction_id": "dc1bd74c-5ade-4e2f-b534-aef46d94a00f",
        "message_id": "29afef30-00eb-4bb4-92d7-145ef91e0bfa",
        "bpp_id": "ref-logistics-app-stage.ondc.org",
        "bpp_uri": "https://ref-logistics-app-dev.thewitslab.com/",
        "timestamp": "2023-10-05T13:03:26.532Z",
        "ttl": "PT30S"
    },
    "message": {
        "update_target": "fulfillment",
        "order": {
            "id": "5cb39038-de64-45f4-ae4e-8c38fc490499",
            "items": [
                {
                    "id": "Express",
                    "fulfillment_id": "27acc85d-2b0e-42fa-b1dd-a6655bed19fd",
                    "category_id": "Express Delivery",
                    "descriptor": {
                        "code": "P2H2P"
                    },
                    "time": {
                        "label": "TAT",
                        "duration": "PT4D",
                        "timestamp": "2023-10-05"
                    }
                }
            ],
            "fulfillments": [
                {
                    "id": "27acc85d-2b0e-42fa-b1dd-a6655bed19fd",
                    "type": "Delivery",
                    "start": {
                        "instructions": {
                            "code": "3",
                            "short_desc": "070147",
                            "long_desc": "Order pickup code."
                        }
                    },
                    "end": {},
                    "tags": [
                        {
                            "code": "state",
                            "list": [
                                {
                                    "code": "ready_to_ship",
                                    "value": "yes"
                                }
                            ]
                        }
                    ]
                }
            ],
            "@ondc/org/linked_order": {
                "items": [
                    {
                        "category_id": "Grocery",
                        "descriptor": {
                            "name": "Atta"
                        },
                        "quantity": {
                            "count": 1,
                            "measure": {
                                "unit": "kilogram",
                                "value": 5
                            }
                        },
                        "price": {
                            "currency": "INR",
                            "value": "300.00"
                        }
                    }
                ],
                "order": {
                    "id": "28fa202b-f3ae-45b3-8283-dc50947ffeb2",
                    "weight": {
                        "unit": "kilogram",
                        "value": 5
                    },
                    "dimensions": {
                        "length": {
                            "unit": "centimeter",
                            "value": 15
                        },
                        "breadth": {
                            "unit": "centimeter",
                            "value": 10
                        },
                        "height": {
                            "unit": "centimeter",
                            "value": 10
                        }
                    }
                }
            },
            "updated_at": "2023-10-05T13:03:26.532Z"
        }
    }
}