{
    "context": {
        "domain": "ONDC:RET11",
        "country": "IND",
        "city": "std:080",
        "action": "search",
        "core_version": "1.2.0",
        "bap_id": "extapi.oyeti.com",
        "bap_uri": "https://extapi.oyeti.com/ecommerce_v2/api",
        "transaction_id": "2acdf567-259b-4f5d-b399-a72ecca66789",
        "message_id": "d7eedcb6-01d5-499c-bef3-13eb498fc5b5",
        "timestamp": "2025-04-29T23:24:36.654Z",
        "ttl": "PT30S"
    },
    "message": {
        "intent": {
            "payment": {
            "@ondc/org/buyer_app_finder_fee_type": "percent",
            "@ondc/org/buyer_app_finder_fee_amount": "3.0"
            },
            "tags": [
            {
                "code": "catalog_inc",
                "list": [
                {
                    "code": "mode",
                    "value": "start"
                }
                ]
            }
            ]
        }
    }
}