{
  "context": {
    "timestamp": "2024-12-09T19:36:53.930Z",
    "bpp_id": "bridge.sellersetu.in/ondc/happypay",
    "ttl": "PT30S",
    "domain": "ONDC:RET11",
    "core_version": "1.2.0",
    "bap_uri": "https://buyer-app-preprod-v2.ondc.org/protocol/v1",
    "country": "IND",
    "message_id": "ccc68917-a244-4525-a105-3a5324d800ba",
    "transaction_id": "c03f2166-5e9f-4e72-a596-57eb43d42418",
    "bpp_uri": "https://bridge.sellersetu.in/ondc/happypay/",
    "action": "on_status",
    "bap_id": "buyer-app-preprod-v2.ondc.org",
    "city": "std:0124"
  },
  "message": {
    "order": {
      "id": "2024-12-09-500331",
      "fulfillments": [
        {
          "id": "mp2_immediate_f1",
          "end": {
            "contact": {
              "phone": "9148043218",
              "email": "chaitanya@sellersetu.in"
            },
            "location": {
              "address": {
                "state": "Haryana",
                "country": "IND",
                "building": "street",
                "locality": "Khandsa Marg",
                "area_code": "122001",
                "city": "Gurugram",
                "name": "Chaitanya Keyal"
              },
              "gps": "28.455714,77.022169"
            },
            "instructions": {
              "long_desc": "No additional delivery instructions",
              "short_desc": "Code",
              "code": "3",
              "name": ""
            },
            "time": {
              "range": {
                "end": "2024-12-09T20:11:50.936Z",
                "start": "2024-12-09T19:56:50.936Z"
              }
            },
            "person": {
              "name": "Chaitanya Keyal"
            }
          },
          "start": {
            "contact": {
              "email": "ikshan@gmail.com",
              "phone": "8882160205"
            },
            "time": {
              "range": {
                "start": "2024-12-09T19:36:50.936Z",
                "end": "2024-12-09T19:56:50.936Z"
              }
            },
            "location": {
              "descriptor": {
                "name": "HappyPay FnB Store"
              },
              "gps": "28.4554726,77.0219019",
              "address": {
                "locality": "Zoological Park Road,  70,    Defence Colony",
                "city": "Gurgaon",
                "area_code": "122001",
                "state": "Haryana"
              }
            },
            "instructions": {
              "long_desc": "Please provide the pickup code to the delivery agent",
              "short_desc": "1340",
              "code": "3",
              "name": ""
            }
          },
          "state": {
            "descriptor": {
              "code": "Packed"
            }
          },
          "type": "Delivery",
          "@ondc/org/provider_name": "MP2",
          "tracking": true,
          "@ondc/org/TAT": "PT55M",
          "tags": [
            {
              "list": [
                {
                  "code": "type",
                  "value": "P2P"
                }
              ],
              "code": "routing"
            }
          ]
        }
      ],
      "updated_at": "2024-12-09T19:36:53.930Z",
      "provider": {
        "id": "0e153d44-00c8-4496-8062-6e1f783be41c",
        "locations": [
          {
            "id": "32a2f074-7fbc-4972-9ea5-6efea53bb4e7"
          }
        ]
      },
      "quote": {
        "ttl": "P1D",
        "price": {
          "currency": "INR",
          "value": "431.0"
        },
        "breakup": [
          {
            "@ondc/org/item_id": "e198d25c-818c-46ba-907f-c62d79dd7a20",
            "@ondc/org/item_quantity": {
              "count": 1
            },
            "title": "Spiced Veggies Pizza",
            "@ondc/org/title_type": "item",
            "price": {
              "value": "300.0",
              "currency": "INR"
            },
            "item": {
              "price": {
                "currency": "INR",
                "value": "300.0"
              },
              "tags": [
                {
                  "code": "type",
                  "list": [
                    {
                      "code": "type",
                      "value": "item"
                    }
                  ]
                }
              ],
              "parent_item_id": "Br5aaCWP/mnV"
            }
          },
          {
            "item": {
              "parent_item_id": "Br5aaCWP/mnV",
              "price": {
                "currency": "INR",
                "value": "50.0"
              },
              "tags": [
                {
                  "list": [
                    {
                      "code": "type",
                      "value": "customization"
                    }
                  ],
                  "code": "type"
                },
                {
                  "list": [
                    {
                      "value": "179051df-6aeb-4b84-9057-4aeff0b8dc48",
                      "code": "id"
                    }
                  ],
                  "code": "parent"
                }
              ]
            },
            "@ondc/org/item_id": "25224a90-9a0a-468f-9dfd-bfbf02e332a0",
            "@ondc/org/item_quantity": {
              "count": 1
            },
            "title": "Extra Cheese",
            "@ondc/org/title_type": "item",
            "price": {
              "currency": "INR",
              "value": "50.0"
            }
          },
          {
            "title": "Dahi Bhalla (P)",
            "@ondc/org/title_type": "item",
            "price": {
              "currency": "INR",
              "value": "50.0"
            },
            "item": {
              "price": {
                "value": "50.0",
                "currency": "INR"
              },
              "tags": [
                {
                  "list": [
                    {
                      "value": "item",
                      "code": "type"
                    }
                  ],
                  "code": "type"
                }
              ],
              "parent_item_id": "09i0sioXP/7Y"
            },
            "@ondc/org/item_id": "9411d55e-3712-4243-a811-07798857595d",
            "@ondc/org/item_quantity": {
              "count": 1
            }
          },
          {
            "price": {
              "currency": "INR",
              "value": "5.0"
            },
            "item": {
              "parent_item_id": "09i0sioXP/7Y",
              "price": {
                "currency": "INR",
                "value": "5.0"
              },
              "tags": [
                {
                  "code": "type",
                  "list": [
                    {
                      "value": "customization",
                      "code": "type"
                    }
                  ]
                },
                {
                  "code": "parent",
                  "list": [
                    {
                      "value": "c4a3d5eb-e2df-47fa-91c0-2cdffefa76dc",
                      "code": "id"
                    }
                  ]
                }
              ]
            },
            "@ondc/org/item_id": "402bc423-488b-4019-9ff6-ef61592d37d9",
            "@ondc/org/item_quantity": {
              "count": 1
            },
            "title": "Extra Curd",
            "@ondc/org/title_type": "item"
          },
          {
            "@ondc/org/title_type": "delivery",
            "price": {
              "value": "26.0",
              "currency": "INR"
            },
            "@ondc/org/item_id": "mp2_immediate_f1",
            "title": "Delivery charges"
          }
        ]
      },
      "state": "In-progress",
      "billing": {
        "phone": "9148043218",
        "created_at": "2024-12-09T19:36:13.413Z",
        "updated_at": "2024-12-09T19:36:13.413Z",
        "name": "Chaitanya Keyal",
        "address": {
          "building": "street",
          "locality": "Khandsa Marg",
          "area_code": "122001",
          "city": "Gurugram",
          "name": "Chaitanya Keyal",
          "state": "Haryana",
          "country": "IND"
        },
        "email": "chaitanya@sellersetu.in"
      },
      "created_at": "2024-12-09T19:36:35.053Z",
      "payment": {
        "tl_method": "http/get",
        "type": "ON-ORDER",
        "@ondc/org/settlement_details": [
          {
            "branch_name": "Delhi",
            "settlement_counterparty": "seller-app",
            "settlement_type": "neft",
            "beneficiary_name": "Seller",
            "upi_address": "seller@paytm",
            "settlement_ifsc_code": "123654789",
            "bank_name": "ICICI",
            "settlement_phase": "sale-amount",
            "settlement_bank_account_no": "123654789"
          }
        ],
        "params": {
          "transaction_id": "order_PVCAhgV7Aylqfu",
          "amount": "431.00",
          "currency": "INR"
        },
        "@ondc/org/buyer_app_finder_fee_amount": "3.0",
        "collected_by": "BAP",
        "@ondc/org/buyer_app_finder_fee_type": "percent",
        "status": "PAID",
        "uri": "https://razorpay.com/"
      },
      "items": [
        {
          "tags": [
            {
              "code": "type",
              "list": [
                {
                  "value": "item",
                  "code": "type"
                }
              ]
            }
          ],
          "id": "e198d25c-818c-46ba-907f-c62d79dd7a20",
          "fulfillment_id": "mp2_immediate_f1",
          "quantity": {
            "count": 1
          },
          "parent_item_id": "Br5aaCWP/mnV"
        },
        {
          "fulfillment_id": "mp2_immediate_f1",
          "quantity": {
            "count": 1
          },
          "parent_item_id": "Br5aaCWP/mnV",
          "tags": [
            {
              "code": "type",
              "list": [
                {
                  "value": "customization",
                  "code": "type"
                }
              ]
            },
            {
              "list": [
                {
                  "value": "179051df-6aeb-4b84-9057-4aeff0b8dc48",
                  "code": "id"
                }
              ],
              "code": "parent"
            }
          ],
          "id": "25224a90-9a0a-468f-9dfd-bfbf02e332a0"
        },
        {
          "parent_item_id": "09i0sioXP/7Y",
          "tags": [
            {
              "code": "type",
              "list": [
                {
                  "code": "type",
                  "value": "item"
                }
              ]
            }
          ],
          "id": "9411d55e-3712-4243-a811-07798857595d",
          "fulfillment_id": "mp2_immediate_f1",
          "quantity": {
            "count": 1
          }
        },
        {
          "id": "402bc423-488b-4019-9ff6-ef61592d37d9",
          "fulfillment_id": "mp2_immediate_f1",
          "quantity": {
            "count": 1
          },
          "parent_item_id": "09i0sioXP/7Y",
          "tags": [
            {
              "code": "type",
              "list": [
                {
                  "code": "type",
                  "value": "customization"
                }
              ]
            },
            {
              "code": "parent",
              "list": [
                {
                  "code": "id",
                  "value": "c4a3d5eb-e2df-47fa-91c0-2cdffefa76dc"
                }
              ]
            }
          ]
        }
      ]
    }
  }
}