{
  "context": {
    "domain": "ONDC:RET11",
    "country": "IND",
    "city": "std:080",
    "action": "on_confirm",
    "core_version": "1.2.0",
    "bap_id": "buyer-app-preprod-v2.ondc.org",
    "bap_uri": "https://buyer-app-preprod-v2.ondc.org/protocol/v1",
    "bpp_id": "extweb.oyeti.com/ecommerce/ondc",
    "bpp_uri": "https://extweb.oyeti.com/ecommerce/ondc/ecommerce/ondc",
    "transaction_id": "e6ee1e7d-9388-4db5-83cd-03d95c428273",
    "message_id": "42c42418-52ef-4635-80d2-e2a312dd0c91",
    "timestamp": "2024-02-02T07:45:41.156Z"
  },
  "message": {
    "order": {
      "id": "2024-02-02-942858",
      "state": "Created",
      "provider": {
        "id": "1039535",
        "locations": [
          {
            "id": "378278"
          }
        ],
        "rateable": true
      },
      "items": [
        {
          "id": "13691021",
          "tags": [
            {
              "code": "type",
              "list": [
                {
                  "code": "type",
                  "value": "item"
                }
              ]
            }
          ],
          "quantity": {
            "count": 1
          },
          "fulfillment_id": "db86eee9-16e4-4b6e-b5c0-c0b6d647788e"
        },
        {
          "id": "13691071",
          "tags": [
            {
              "code": "type",
              "list": [
                {
                  "code": "type",
                  "value": "item"
                }
              ]
            }
          ],
          "quantity": {
            "count": 1
          },
          "fulfillment_id": "db86eee9-16e4-4b6e-b5c0-c0b6d647788e"
        }
      ],
      "billing": {
        "name": "Gagan Reddy",
        "email": "venky5007.ror@gmail.com",
        "phone": "8073415788",
        "address": {
          "city": "Bengaluru",
          "name": "Gagan Reddy",
          "state": "Karnataka",
          "country": "IND",
          "building": "His Highness Nalwadi Krishna Raja Wadiyar Hall, XHCR+GRC",
          "locality": "Cubbon Park Road",
          "area_code": "560001"
        },
        "created_at": "2024-02-02T07:45:26.812Z",
        "updated_at": "2024-02-02T07:45:26.812Z"
      },
      "fulfillments": [
        {
          "id": "db86eee9-16e4-4b6e-b5c0-c0b6d647788e",
          "end": {
            "contact": {
              "email": "venky5007.ror@gmail.com",
              "phone": "8073415788"
            },
            "person": {
              "name": "Gagan Reddy"
            },
            "location": {
              "gps": "12.9753850802527,77.5887429714203",
              "address": {
                "city": "Bengaluru",
                "name": "Gagan Reddy",
                "state": "Karnataka",
                "country": "IND",
                "building": "His Highness Nalwadi Krishna Raja Wadiyar Hall, XHCR+GRC",
                "locality": "Cubbon Park Road",
                "area_code": "560001"
              }
            },
            "time": {
              "range": {
                "start": "2024-02-02T13:15:41.889Z",
                "end": "2024-02-02T14:15:41.889Z"
              }
            }
          },
          "type": "Delivery",
          "start": {
            "location": {
              "id": "378278",
              "descriptor": {
                "name": "Nandyal Chefs"
              },
              "address": {
                "locality": "Nunegundlapalli, Ambedkar Veedhi, Bengaluru, Bangalore Division, Karnataka, India",
                "city": "Bengaluru",
                "area_code": "560001",
                "state": "Karnataka"
              },
              "gps": "12.9713073,77.5920295"
            },
            "contact": {
              "phone": "7893847511",
              "email": "venkateshmurapureddy@gmail.com"
            },
            "time": {
              "range": {
                "start": "2024-02-02T13:15:41.889Z",
                "end": "2024-02-02T14:15:41.889Z"
              }
            }
          },
          "tracking": true,
          "state": {
            "descriptor": {
              "code": "Pending"
            }
          },
          "@ondc/org/provider_name": "db86eee9-16e4-4b6e-b5c0-c0b6d647788e"
        }
      ],
      "quote": {
        "price": {
          "currency": "INR",
          "value": "539.08"
        },
        "breakup": [
          {
            "@ondc/org/item_id": "13691021",
            "@ondc/org/item_quantity": {
              "count": 1
            },
            "title": "Almond Filter Coffee",
            "@ondc/org/title_type": "item",
            "price": {
              "currency": "INR",
              "value": "200.0"
            },
            "item": {
              "price": {
                "currency": "INR",
                "value": "200.0"
              },
              "tags": [
                {
                  "code": "type",
                  "list": [
                    {
                      "code": "type",
                      "value": "item"
                    }
                  ]
                }
              ]
            }
          },
          {
            "@ondc/org/item_id": "13691071",
            "@ondc/org/item_quantity": {
              "count": 1
            },
            "title": "Venky Masala Tea",
            "@ondc/org/title_type": "item",
            "price": {
              "currency": "INR",
              "value": "200.0"
            },
            "item": {
              "price": {
                "currency": "INR",
                "value": "200.0"
              },
              "tags": [
                {
                  "code": "type",
                  "list": [
                    {
                      "code": "type",
                      "value": "item"
                    }
                  ]
                }
              ]
            }
          },
          {
            "@ondc/org/item_id": "db86eee9-16e4-4b6e-b5c0-c0b6d647788e",
            "title": "Delivery charges",
            "@ondc/org/title_type": "delivery",
            "price": {
              "currency": "INR",
              "value": "122.38"
            }
          },
          {
            "@ondc/org/item_id": "db86eee9-16e4-4b6e-b5c0-c0b6d647788e",
            "title": "Packing charges",
            "@ondc/org/title_type": "packing",
            "price": {
              "currency": "INR",
              "value": "1.0"
            }
          },
          {
            "@ondc/org/item_id": "db86eee9-16e4-4b6e-b5c0-c0b6d647788e",
            "title": "Convenience Fee",
            "@ondc/org/title_type": "misc",
            "price": {
              "currency": "INR",
              "value": "15.7"
            }
          }
        ],
        "ttl": "PT30S"
      },
      "payment": {
        "uri": "https://juspay.in/",
        "type": "ON-ORDER",
        "params": {
          "amount": "539.08",
          "currency": "INR",
          "transaction_id": "65d92de0-51ea-4bd0-81fd-97661787227d"
        },
        "status": "PAID",
        "tl_method": "http/get",
        "collected_by": "BAP",
        "@ondc/org/settlement_details": [
          {
            "bank_name": "SB",
            "branch_name": "CNN",
            "upi_address": "gft@oksbi",
            "settlement_type": "neft",
            "beneficiary_name": "Perfect Fit",
            "settlement_phase": "sale-amount",
            "settlement_ifsc_code": "SBIN12345",
            "settlement_counterparty": "seller-app",
            "settlement_bank_account_no": "1000000000"
          }
        ],
        "@ondc/org/buyer_app_finder_fee_type": "percent",
        "@ondc/org/buyer_app_finder_fee_amount": "3.0"
      },
      "tags": [
        {
          "code": "bpp_terms",
          "list": [
            {
              "code": "tax_number",
              "value": "29AAECN5025F1ZK"
            }
          ]
        },
        {
          "code": "bap_terms",
          "list": [
            {
              "code": "tax_number",
              "value": "39AAECN5025F1ZK"
            }
          ]
        }
      ],
      "created_at": "2024-02-02T07:45:40.156Z",
      "updated_at": "2024-02-02T07:45:41.156Z"
    }
  }
}