{
  "context": {
    "domain": "nic2004:60232",
    "country": "IND",
    "city": "std:0124",
    "action": "on_track",
    "core_version": "1.2.0",
    "bap_id": "bridge.sellersetu.in",
    "bap_uri": "https://bridge.sellersetu.in/ondc",
    "bpp_id": "preprod.logistics-seller.mp2.in",
    "bpp_uri": "https://preprod.logistics-seller.mp2.in/ondc",
    "transaction_id": "b6cfe371-ff01-4345-83c5-b30f9faec500",
    "message_id": "31dc0b5e-da91-4ffb-9d42-22ce2d47591c",
    "timestamp": "2024-09-03T18:00:09.732Z",
    "ttl": "PT30S",
    "req_path": "bridge.sellersetu.in"
  },
  "message": {
    "tracking": {
      "id": "mp2_sdd_f1",
      "url": "https://track.mp2.in/track/2024-09-03-552132",
      "location": {
        "gps": "12.345556,78.234555",
        "time": {
          "timestamp": "2024-09-03T18:00:07.747Z"
        },
        "updated_at": "2024-09-03T18:00:07.747Z"
      },
      "status": "active",
      "tags": [
        {
          "code": "order",
          "list": [
            {
              "code": "id",
              "value": "2024-09-03-552132"
            }
          ]
        },
        {
          "code": "config",
          "list": [
            {
              "code": "attr",
              "value": "tracking.location.gps"
            },
            {
              "code": "type",
              "value": "live_poll"
            }
          ]
        }
      ]
    }
  }
}