{
  "context": {
    "domain": "ONDC:RET10",
    "action": "update",
    "core_version": "1.2.0",
    "bap_id": "buyer-app-preprod-v2.ondc.org",
    "bap_uri": "https://buyer-app-preprod-v2.ondc.org/protocol/v1",
    "bpp_id": "api.greenreceipt.in",
    "bpp_uri": "https://api.greenreceipt.in/ondc",
    "transaction_id": "0b26e1cf-6abe-4cbd-9710-190697586f93",
    "message_id": "a80db905-7ca2-4575-8e75-49190627aec2",
    "city": "std:0124",
    "country": "IND",
    "timestamp": "2024-06-27T13:21:43.949Z"
  },
  "message": {
    "update_target": "payment",
    "order": {
      "id": "2024-06-27-246526",
      "fulfillments": [
        {
          "id": "667d6742abce08b4235467cb",
          "type": "Return"
        }
      ],
      "payment": {
        "@ondc/org/settlement_details": [
          {
            "settlement_counterparty": "buyer",
            "settlement_phase": "refund",
            "settlement_type": "netbanking",
            "settlement_amount": "160",
            "settlement_timestamp": "2024-06-27T13:21:43.949Z"
          }
        ]
      }
    }
  }
}
