{
  "context": {
    "domain": "ONDC:RET10",
    "location": {
      "country": {
        "code": "IND"
      },
      "city": {
        "code": "*"
      }
    },
    "core_version": "2.0.0",
    "bpp_id": "ondc.ogoshop.in",
    "bap_id": "igm-mock-service.ondc.org/igm-protocol-server-preprod/ondc",
    "bpp_uri": "https://ondc.ogoshop.in/api/ondc",
    "bap_uri": "https://igm-mock-service.ondc.org/igm-protocol-server-preprod/ondc",
    "transaction_id": "160da641-cf39-4a1a-8725-5f46d3f255b3",
    "message_id": "26e94d05-b64f-4312-97e8-7b3a14f81460",
    "timestamp": "2025-03-04T07:51:10.294Z",
    "ttl": "PT30S"
  },
  "message": {
    "issue_id": "30f66c9e-125d-40a0-a700-513ffc4927c5"
  }
}