{
    "context": {
        "domain": "ONDC:RET12",
        "action": "search",
        "country": "IND",
        "city": "std:080",
        "core_version": "1.2.0",
        "bap_id": "buyer-preprod.aurikatech.com",
        "bap_uri": "https://buyer-preprod.aurikatech.com/protocol/v1",
        "transaction_id": "47afcd21-6151-4567-959c-85b8211fcfb4",
        "message_id": "22e68f0d-8fcf-41c3-a335-efc2ae9cd07a",
        "timestamp": "2024-11-20T11:39:45.397Z",
        "ttl": "PT30S"
    },
    "message": {
        "intent": {
            "fulfillment": {
                "type": "Delivery"
            },
            "payment": {
                "@ondc/org/buyer_app_finder_fee_type": "percent",
                "@ondc/org/buyer_app_finder_fee_amount": "3"
            }
        }
    }
}