{
    "context": {
        "domain": "ONDC:RET10",
        "country": "IND",
        "city": "std:0120",
        "action": "select",
        "core_version": "1.2.0",
        "bap_id": "buyer-app-preprod-v2.ondc.org",
        "bap_uri": "https://buyer-app-preprod-v2.ondc.org/protocol/v1",
        "bpp_uri": "https://smartsell.samhita.org/ondc/api/v1",
        "transaction_id": "c43eeb51-b0bb-4d30-8af8-a31ff01e9fa7",
        "message_id": "07c9f23c-14b7-4a20-b513-d3282f4187fb",
        "timestamp": "2025-03-27T10:26:52.959Z",
        "bpp_id": "smartsell.samhita.org",
        "ttl": "PT30S"
    },
    "message": {
        "order": {
            "items": [
                {
                    "id": "ondc109",
                    "quantity": {
                        "count": 4
                    },
                    "location_id": "950818"
                }
            ],
            "provider": {
                "id": "28",
                "locations": [
                    {
                        "id": "950818"
                    }
                ]
            },
            "fulfillments": [
                {
                    "end": {
                        "location": {
                            "gps": "28.629649,77.377822",
                            "address": {
                                "area_code": "201301"
                            }
                        }
                    }
                }
            ]
        }
    }
}