{
    "context":{
       "domain":"ONDC:RET10",
       "country":"IND",
       "city":"std:080",
       "action":"on_status",
       "core_version":"1.2.0",
       "bap_id":"ref-app-buyer-staging-v2.ondc.org",
       "bap_uri":"https://ref-app-buyer-staging-v2.ondc.org/protocol/v1",
       "bpp_uri":"https://ondc.moreretail.net/bapl",
       "transaction_id":"7b4df6ff-df98-4438-9e9e-1e0c750b23c5",
       "message_id":"b9aaeee2-27b6-4df0-9603-e8db4bccafa2",
       "timestamp":"2023-12-06T06:55:57.732Z",
       "bpp_id":"ondc.moreretail.net",
       "ttl":"PT30S"
    },
    "message":{
       "order":{
          "id":"2023-12-06-154962",
          "state":"In-progress",
          "provider":{
             "id":"1594",
             "locations":[
                {
                   "id":"1594"
                }
             ]
          },
          "items":[
             {
                "id":"100723962",
                "fulfillment_id":"F1",
                "quantity":{
                   "count":1.0
                }
             },
             {
                "id":"101981537",
                "fulfillment_id":"F1",
                "quantity":{
                   "count":1.0
                }
             }
          ],
          "billing":{
             "name":" ",
             "phone":"9380322239",
             "address":{
                "city":"",
                "name":"Chinmaya M G we work",
                "state":"",
                "country":"IND",
                "building":"Nagasandra Road",
                "locality":"Nagasandra Road",
                "area_code":"560071"
             },
             "created_at":"2023-12-06T06:31:14.197Z",
             "updated_at":"2023-12-06T06:31:14.197Z"
          },
          "fulfillments":[
             {
                "id":"F1",
                "@ondc/org/provider_name":"SM Bangalore Domlur",
                "type":"Delivery",
                "tracking":false,
                "@ondc/org/TAT":"PT60M",
                "state":{
                   "descriptor":{
                      "code":"Out-for-delivery"
                   }
                },
                "start":{
                   "location":{
                      "descriptor":{
                         "name":"SM Bangalore Domlur"
                      },
                      "gps":"12.95956,77.63842",
                      "address":{
                         "city":"Bengaluru",
                         "state":"KA",
                         "locality":"No 296 7th Cross  Domlur Bengaluru 560071",
                         "area_code":"560071"
                      }
                   },
                   "time":{
                      "timestamp":"2023-12-06T06:54:11.740Z"
                   },
                   "contact":{
                      "phone":"9606053373"
                   }
                },
                "end":{
                   "location":{
                      "gps":"12.95956,77.63842",
                      "address":{
                         "city":"",
                         "name":"Chinmaya M G we work",
                         "state":"",
                         "country":"IND",
                         "building":"Nagasandra Road",
                         "locality":"Nagasandra Road",
                         "area_code":"560071"
                      }
                   },
                   "time":{
                      "timestamp":"2023-12-06T06:54:11.740Z"
                   },
                   "contact":{
                      "phone":"9380322239"
                   }
                }
             }
          ],
          "quote":{
             "price":{
                "currency":"INR",
                "value":"442.0"
             },
             "breakup":[
                {
                   "@ondc/org/item_id":"100723962",
                   "@ondc/org/item_quantity":{
                      "count":1.0
                   },
                   "title":"Savlon Antiseptic Disinfectant Liquid, 200 ml Bottle",
                   "@ondc/org/title_type":"item",
                   "price":{
                      "currency":"INR",
                      "value":"92.00"
                   },
                   "item":{
                      "price":{
                         "currency":"INR",
                         "value":"92.00"
                      }
                   }
                },
                {
                   "@ondc/org/item_id":"100723962",
                   "title":"Tax",
                   "@ondc/org/title_type":"tax",
                   "price":{
                      "currency":"INR",
                      "value":"0"
                   }
                },
                {
                   "@ondc/org/item_id":"100723962",
                   "title":"Discount",
                   "@ondc/org/title_type":"discount",
                   "price":{
                      "currency":"INR",
                      "value":"0"
                   }
                },
                {
                   "@ondc/org/item_id":"101981537",
                   "@ondc/org/item_quantity":{
                      "count":1.0
                   },
                   "title":"Axe Dark Temptation Body Spray Deo, 215 ml Bottle",
                   "@ondc/org/title_type":"item",
                   "price":{
                      "currency":"INR",
                      "value":"350.00"
                   },
                   "item":{
                      "price":{
                         "currency":"INR",
                         "value":"350.00"
                      }
                   }
                },
                {
                   "@ondc/org/item_id":"101981537",
                   "title":"Tax",
                   "@ondc/org/title_type":"tax",
                   "price":{
                      "currency":"INR",
                      "value":"0"
                   }
                },
                {
                   "@ondc/org/item_id":"101981537",
                   "title":"Discount",
                   "@ondc/org/title_type":"discount",
                   "price":{
                      "currency":"INR",
                      "value":"0"
                   }
                },
                {
                   "@ondc/org/item_id":"F1",
                   "title":"Delivery charges",
                   "@ondc/org/title_type":"delivery",
                   "price":{
                      "currency":"INR",
                      "value":"0"
                   }
                },
                {
                   "@ondc/org/item_id":"F1",
                   "title":"Packing charges",
                   "@ondc/org/title_type":"packing",
                   "price":{
                      "currency":"INR",
                      "value":"0"
                   }
                },
                {
                   "@ondc/org/item_id":"F1",
                   "title":"Convenience Fee",
                   "@ondc/org/title_type":"misc",
                   "price":{
                      "currency":"INR",
                      "value":"0"
                   }
                }
             ],
             "ttl":"P1D"
          },
          "payment":{
             "uri":"https://juspay.in/",
             "type":"ON-ORDER",
             "params":{
                "amount":"442",
                "currency":"INR",
                "transaction_id":"eb7b5282-dd56-49c4-bfb9-1941e9bbf402"
             },
             "status":"PAID",
             "tl_method":"http/get",
             "collected_by":"BAP",
             "@ondc/org/buyer_app_finder_fee_type":"percent",
             "@ondc/org/buyer_app_finder_fee_amount":"3.0"
          },
          "created_at":"2023-12-06T06:55:57.848602Z",
          "updated_at":"2023-12-06T06:55:57.848602Z",
          "documents":[
             {
                "url":"https://invoice-credit-note.s3.amazonaws.com/MoreRetail-Invoice-159446918.pdf?X-Amz-Algorithm=AWS4-HMAC-SHA256&X-Amz-Credential=AKIASREM227VANASTPFG%2F20231206%2Fap-south-1%2Fs3%2Faws4_request&X-Amz-Date=20231206T065557Z&X-Amz-Expires=21600&X-Amz-SignedHeaders=host&X-Amz-Signature=d663a97c82a17c400d9a90369d7a489c7d8ef20372193e904dbfca781979b973",
                "label":"Invoice"
             }
          ]
       }
    }
 }