{
    "context": {
        "domain": "ONDC:RET10",
        "country": "IND",
        "city": "std:080",
        "action": "status",
        "core_version": "1.2.0",
        "bap_id": "ondc-b2c-buyer-api.trafyn.site",
        "bap_uri": "https://ondc-b2c-buyer-api.trafyn.site/",
        "bpp_id": "ondc-seller-api.trafyn.site",
        "bpp_uri": "https://ondc-seller-api.trafyn.site/",
        "transaction_id": "6114f8e6-7711-49d4-8c14-31bd06ea9cb2",
        "message_id": "1716396898100",
        "timestamp": "2024-05-22T16:54:58.100Z",
        "ttl": "PT30S"
    },
    "message": {
        "order_id": "a68ced2f-7ed3-41f6-a112-1186197919e7"
    }
}