{    "context": {
  "domain": "ONDC:RET11",
  "action": "search",
  "country": "IND",
  "city": "*",
  "core_version": "1.2.0",
  "bap_id": "ref-app-buyer-staging-v2.ondc.org",
  "bap_uri": "https://ref-app-buyer-staging-v2.ondc.org/protocol/v1",
  "transaction_id": "3d3c4188-ba61-4060-bca0-52500791001f",
  "message_id": "edaa384c-28c3-4108-acfb-79771cf7de9b",
  "timestamp": "2024-02-28T16:04:32.485Z",
  "ttl": "PT30S"
},
  "message": {
    "intent": {
      "payment": {
        "@ondc/org/buyer_app_finder_fee_type": "percent",
        "@ondc/org/buyer_app_finder_fee_amount": "3"
      },
      "tags": [
        {
          "code": "catalog_inc",
          "list": [
            {
              "code": "mode",
              "value": "start"
            }
          ]
        }
      ]
    }
  }}