{
    "context": {
      "action": "status",
      "transaction_id": "88a34fe5-7215-4e86-9c05-98e384c4f18f",
      "message_id": "7f235f7a-4f6a-4056-bb63-7bf228a978d7",
      "city": "std:080",
      "domain": "ONDC:RET11",
      "country": "IND",
      "core_version": "1.2.0",
      "timestamp": "2024-06-28T10:01:32.164Z",
      "bap_id": "beta.mystore.in",
      "bap_uri": "https://beta.mystore.in/ondc/1.0/",
      "bpp_id": "api.test.esamudaay.com/ondc/sdk/bpp/retail/esamudaay",
      "bpp_uri": "https://api.test.esamudaay.com/ondc/sdk/bpp/retail/esamudaay",
      "ttl": "PT30S"
    },
    "message": {
      "order_id": "667e8112825c6d719912648f"
      }
    }
  