{
            "context": {
                "domain": "ONDC:RET10",
                "action": "search",
                "country": "IND",
                "city": "std:020",
                "core_version": "1.2.0",
                "bap_id": "buyer-app-preprod-v2.ondc.org",
                "bap_uri": "https://buyer-app-preprod-v2.ondc.org/protocol/v1",
                "transaction_id": "a904fd79-f63c-4baf-a73f-ac88ea767a04",
                "message_id": "d8a61d34-486c-4124-af14-4ce2b0214f40",
                "timestamp": "2024-04-09T06:00:01.493Z",
                "ttl": "PT30S"
            },
            "message": {
                "intent": {
                    "fulfillment": {
                        "type": "Delivery"
                    },
                    "payment": {
                        "@ondc/org/buyer_app_finder_fee_type": "percent",
                        "@ondc/org/buyer_app_finder_fee_amount": "3"
                    }
                }
            }
        }
