{
    "context": {
        "domain": "ONDC:RET14",
        "action": "search",
        "country": "IND",
        "city": "std:0124",
        "core_version": "1.2.0",
        "bap_id": "buyer-app-preprod-v2.ondc.org",
        "bap_uri": "https://buyer-app-preprod-v2.ondc.org/protocol/v1",
        "transaction_id": "f2ea5775-24e0-4734-a842-10b55791df76",
        "message_id": "485a25f4-d7f1-43d5-a1f2-9a5415b13c2a",
        "timestamp": "2024-07-17T06:12:42.723Z",
        "ttl": "PT30M"
    },
    "message": {
        "intent": {
            "fulfillment": {
                "type": "Delivery"
            },
            "payment": {
                "@ondc/org/buyer_app_finder_fee_type": "percent",
                "@ondc/org/buyer_app_finder_fee_amount": "3"
            }
        }
    }
}