{"context":{"ttl":"PT30S","city":"std:080","action":"select","bap_id":"buyer-app-preprod-v2.ondc.org","bpp_id":"b-ondc-seller-bpp.nlincs.in","domain":"ONDC:RET10","bap_uri":"https://buyer-app-preprod-v2.ondc.org/protocol/v1","bpp_uri":"https://b-ondc-seller-bpp.nlincs.in/bpp","country":"IND","timestamp":"2024-02-08T12:53:12.877Z","message_id":"00280356-d39e-475d-b2dc-336549fd0c2c","core_version":"1.2.0","transaction_id":"e82d0056-05f1-43e3-b187-4646ba696ffa"},"message":{"order":{"items":[{"id":"102","quantity":{"count":3},"location_id":"LOC560005"},{"id":"103","quantity":{"count":1},"location_id":"LOC560005"}],"provider":{"id":"20971","locations":[{"id":"LOC560005"}]},"fulfillments":[{"end":{"location":{"gps":"12.999701970586852,77.62108020227963","address":{"area_code":"560005"}}}}]}}}