{
    "context": {
        "domain": "nic2004:60232",
        "action": "init",
        "core_version": "1.2.0",
        "bap_id": "sellerpreprod.easypay.co.in",
        "bap_uri": "https://sellerpreprod.easypay.co.in/ecommerce/ondc/seller-logistic",
        "bpp_id": "preprod.logistics-seller.mp2.in",
        "bpp_uri": "https://preprod.logistics-seller.mp2.in/ondc",
        "transaction_id": "d01ef803-0953-42ce-affc-bcf28bd73cf2EP",
        "message_id": "123-7544992818",
        "city": "std:020",
        "country": "IND",
        "timestamp": "2024-09-25T07:06:12.355Z",
        "ttl": "PT30S"
    },
    "message": {
        "order": {
            "provider": {
                "id": "MP2"
            },
            "items": [
                {
                    "id": "mp2_immediate",
                    "fulfillment_id": "mp2_immediate_f1",
                    "category_id": "Immediate Delivery",
                    "descriptor": {
                        "code": "P2P"
                    }
                }
            ],
            "billing": {
                "name": "Easy Pay Pvt Ltd",
                "address": {
                    "name": "2",
                    "building": "Tower C,Tech Park One",
                    "locality": "Yerwada",
                    "city": "Pune",
                    "state": "Maharashtra",
                    "country": "India",
                    "area_code": "411006"
                },
                "email": "contact@easypay.in",
                "phone": "7486874868",
                "tax_number": "27AADCE6257B1ZU",
                "created_at": "2024-09-25T07:06:12.355Z",
                "updated_at": "2024-09-25T07:06:12.355Z"
            },
            "fulfillments": [
                {
                    "id": "mp2_immediate_f1",
                    "type": "Delivery",
                    "start": {
                        "location": {
                            "gps": "18.523481,73.863861",
                            "address": {
                                "name": "Jay SuperMart",
                                "building": "Viman nagar",
                                "locality": "Pune",
                                "city": "Pune City",
                                "state": "MAHARASHTRA",
                                "country": "India",
                                "area_code": "411011"
                            }
                        },
                        "contact": {
                            "phone": "8849150463",
                            "email": "jay@gmail.com"
                        }
                    },
                    "end": {
                        "location": {
                            "gps": "18.5621203, 73.9140104",
                            "address": {
                                "name": "core B Solitaire Business Hub Viman Nagar",
                                "locality": "Viman Nagar",
                                "city": "Pune",
                                "state": "Maharashtra",
                                "country": "India",
                                "area_code": "411014",
                                "building": "5070"
                            }
                        },
                        "contact": {
                            "phone": "9168291386"
                        }
                    }
                }
            ],
            "payment": {
                "type": "POST-FULFILLMENT",
                "collected_by": "BAP"
            }
        }
    }
}