{
    "context": {
        "domain": "ONDC:RET12",
        "country": "IND",
        "city": "std:0120",
        "action": "on_status",
        "core_version": "1.2.0",
        "bap_id": "buyer-app-preprod-v2.ondc.org",
        "bap_uri": "https://buyer-app-preprod-v2.ondc.org/protocol/v1",
        "bpp_uri": "https://ondc.ecomviser.com/api/v1",
        "transaction_id": "aba2c1e1-c0c4-4dbe-9947-bb33bade9470",
        "message_id": "67bed68430c12b5aec2fd-1de2",
        "timestamp": "2025-02-26T08:53:24.199Z",
        "bpp_id": "ondc.ecomviser.com",
        "ttl": "PT30S"
    },
    "message": {
        "order": {
            "id": "2025-02-26-865001",
            "state": "Cancelled",
            "provider": {
                "id": "87",
                "locations": [
                    {
                        "id": "86"
                    }
                ]
            },
            "items": [
                {
                    "id": "495",
                    "fulfillment_id": "161",
                    "quantity": {
                        "count": 0
                    },
                    "tags": [
                        {
                            "code": "type",
                            "list": [
                                {
                                    "code": "type",
                                    "value": "item"
                                }
                            ]
                        }
                    ]
                },
                {
                    "id": "495",
                    "fulfillment_id": "rto-shipping",
                    "quantity": {
                        "count": 1
                    }
                }
            ],
            "billing": {
                "name": "Dheeraj Office",
                "email": "dheeraj@webkul.in",
                "phone": "6765986340",
                "address": {
                    "city": "Noida",
                    "name": "Dheeraj Office",
                    "state": "Uttar Pradesh",
                    "country": "IND",
                    "building": "Ginger Noida Sector-63",
                    "locality": "Shaheed Hawaldar Padam Singh Dhama Marg",
                    "area_code": "201301"
                },
                "created_at": "2025-02-26T08:50:50.114Z",
                "updated_at": "2025-02-26T08:50:50.114Z"
            },
            "fulfillments": [
                {
                    "id": "161",
                    "end": {
                        "time": {
                            "range": {
                                "start": "2025-02-26T08:53:11.776Z",
                                "end": "2025-02-26T09:23:11.776Z"
                            }
                        },
                        "person": {
                            "name": "Dheeraj Office"
                        },
                        "contact": {
                            "email": "dheeraj@webkul.in",
                            "phone": "6765986340"
                        },
                        "location": {
                            "gps": "28.625401,77.375175",
                            "address": {
                                "city": "Noida",
                                "name": "Dheeraj Office",
                                "state": "Uttar Pradesh",
                                "country": "IND",
                                "building": "Ginger Noida Sector-63",
                                "locality": "Shaheed Hawaldar Padam Singh Dhama Marg",
                                "area_code": "201301"
                            }
                        }
                    },
                    "type": "Delivery",
                    "start": {
                        "time": {
                            "range": {
                                "start": "2025-02-26T08:51:20.249Z",
                                "end": "2025-02-26T08:51:20.249Z"
                            }
                        },
                        "contact": {
                            "email": "support@webkul.in",
                            "phone": "9876543210"
                        },
                        "location": {
                            "id": "86",
                            "gps": "28.62972640,77.37783230",
                            "address": {
                                "city": "Gautam Buddh Nagar",
                                "state": "Uttar Pradesh",
                                "locality": "Sector-63",
                                "area_code": "201301"
                            },
                            "descriptor": {
                                "name": "Dheeraj Fashion"
                            }
                        }
                    },
                    "state": {
                        "descriptor": {
                            "code": "Cancelled"
                        }
                    },
                    "tracking": false,
                    "@ondc/org/TAT": "PT120M",
                    "@ondc/org/provider_name": "ondc.ecomviser.com",
                    "tags": [
                        {
                            "code": "cancel_request",
                            "list": [
                                {
                                    "code": "retry_count",
                                    "value": "3"
                                },
                                {
                                    "code": "rto_id",
                                    "value": "rto-shipping"
                                },
                                {
                                    "code": "reason_id",
                                    "value": "011"
                                },
                                {
                                    "code": "initiated_by",
                                    "value": "ondc.ecomviser.com"
                                }
                            ]
                        },
                        {
                            "code": "precancel_state",
                            "list": [
                                {
                                    "code": "fulfillment_state",
                                    "value": "Out-for-delivery"
                                },
                                {
                                    "code": "updated_at",
                                    "value": "2025-02-26T08:52:38.787Z"
                                }
                            ]
                        }
                    ]
                },
                {
                    "id": "rto-shipping",
                    "type": "RTO",
                    "@ondc/org/provider_name": "ondc.ecomviser.com",
                    "state": {
                        "descriptor": {
                            "code": "RTO-Delivered"
                        }
                    },
                    "start": {
                        "time": {
                            "range": {
                                "end": "2025-02-26T09:51:21.320Z",
                                "start": "2025-02-26T08:51:21.320Z"
                            }
                        },
                        "person": {
                            "name": "Dheeraj Office"
                        },
                        "contact": {
                            "email": "dheeraj@webkul.in",
                            "phone": "6765986340"
                        },
                        "location": {
                            "gps": "28.625401,77.375175",
                            "address": {
                                "city": "Noida",
                                "name": "Dheeraj Office",
                                "state": "Uttar Pradesh",
                                "country": "IND",
                                "building": "Ginger Noida Sector-63",
                                "locality": "Shaheed Hawaldar Padam Singh Dhama Marg",
                                "area_code": "201301"
                            }
                        }
                    },
                    "end": {
                        "contact": {
                            "email": "support@webkul.in",
                            "phone": "9876543210"
                        },
                        "location": {
                            "id": "86",
                            "gps": "28.62972640,77.37783230",
                            "address": {
                                "city": "Gautam Buddh Nagar",
                                "state": "Uttar Pradesh",
                                "locality": "Sector-63",
                                "area_code": "201301"
                            },
                            "descriptor": {
                                "name": "Dheeraj Fashion"
                            }
                        }
                    },
                    "tags": [
                        {
                            "code": "quote_trail",
                            "list": [
                                {
                                    "code": "type",
                                    "value": "item"
                                },
                                {
                                    "code": "id",
                                    "value": "495"
                                },
                                {
                                    "code": "currency",
                                    "value": "INR"
                                },
                                {
                                    "code": "value",
                                    "value": "-100"
                                }
                            ]
                        }
                    ]
                }
            ],
            "quote": {
                "ttl": "PT6H",
                "price": {
                    "value": "3.54",
                    "currency": "INR"
                },
                "breakup": [
                    {
                        "item": {
                            "price": {
                                "value": "100",
                                "currency": "INR"
                            }
                        },
                        "price": {
                            "value": "0",
                            "currency": "INR"
                        },
                        "title": "Pouma T-Shirt",
                        "@ondc/org/item_id": "495",
                        "@ondc/org/title_type": "item",
                        "@ondc/org/item_quantity": {
                            "count": 0
                        }
                    },
                    {
                        "price": {
                            "value": "3.54",
                            "currency": "INR"
                        },
                        "title": "Convenience fee",
                        "@ondc/org/item_id": "161",
                        "@ondc/org/title_type": "misc"
                    },
                    {
                        "price": {
                            "value": "0",
                            "currency": "INR"
                        },
                        "title": "Delivery charges",
                        "@ondc/org/item_id": "161",
                        "@ondc/org/title_type": "delivery"
                    }
                ]
            },
            "payment": {
                "uri": "https://razorpay.com/",
                "type": "ON-ORDER",
                "params": {
                    "amount": "103.54",
                    "currency": "INR",
                    "transaction_id": "order_Q0HNXq4OqCM3No"
                },
                "status": "PAID",
                "tl_method": "http/get",
                "collected_by": "BAP",
                "@ondc/org/settlement_details": [
                    {
                        "bank_name": "AXIS BANK LIMITED",
                        "branch_name": "Sector 62 Noida",
                        "settlement_type": "neft",
                        "beneficiary_name": "Webkul Software Private Limited",
                        "settlement_phase": "sale-amount",
                        "settlement_status": "NOT-PAID",
                        "settlement_ifsc_code": "UTIB0000723",
                        "settlement_counterparty": "seller-app",
                        "settlement_bank_account_no": "913020023840783"
                    }
                ],
                "@ondc/org/buyer_app_finder_fee_type": "percent",
                "@ondc/org/buyer_app_finder_fee_amount": "3.0"
            },
            "created_at": "2025-02-26T08:51:14.848Z",
            "updated_at": "2025-02-26T09:23:24.781Z"
        }
    }
}